heatherrd/__init__.py
heatherrd/protocol.py
heatherrd/relay.py
heatherrd/server.py
heatherrd-1.0.0.dist-info/top_level.txt
heatherrd-1.0.0.dist-info/entry_points.txt
heatherrd-1.0.0.dist-info/METADATA
heatherrd-1.0.0.dist-info/DESCRIPTION.rst
heatherrd-1.0.0.dist-info/metadata.json
heatherrd-1.0.0.dist-info/WHEEL
heatherrd-1.0.0.dist-info/RECORD
