Metadata-Version: 2.0
Name: heatherrd
Version: 1.0.0
Summary: This is the heatherrd project.
Home-page: https://github.com/smn/heatherrd
Author: Praekelt Foundation
Author-email: dev@praekeltfoundation.org
License: BSD
Keywords: heatherrd
Platform: UNKNOWN
Classifier: Intended Audience :: Developers
Classifier: Natural Language :: English
Classifier: Programming Language :: Python :: 2.7
Requires-Dist: Klein (==15.3.1)
Requires-Dist: click (==6.2)
Requires-Dist: treq (==15.1.0)
Requires-Dist: autobahn (==0.12.1)
